htpy/__init__.py
htpy/_attributes.py
htpy/_contexts.py
htpy/_elements.py
htpy/_fragments.py
htpy/_legacy_rendering.py
htpy/_rendering.py
htpy/_types.py
htpy/_with_children.py
htpy/django.py
htpy/html2htpy.py
htpy/py.typed
htpy-25.10.0.dist-info/licenses/LICENSE
htpy-25.10.0.dist-info/METADATA
htpy-25.10.0.dist-info/WHEEL
htpy-25.10.0.dist-info/entry_points.txt
htpy-25.10.0.dist-info/top_level.txt
htpy-25.10.0.dist-info/RECORD
