Metadata-Version: 2.4
Name: htpy
Version: 25.10.0
Summary: htpy - HTML in Python
Author-email: Andreas Pelme <andreas@pelme.se>
License-Expression: MIT
Project-URL: Homepage, https://htpy.dev
Project-URL: Repository, https://github.com/pelme/htpy
Project-URL: Documentation, https://htpy.dev
Project-URL: Issues, https://github.com/pelme/htpy/issues
Classifier: Programming Language :: Python :: 3
Classifier: Intended Audience :: Developers
Classifier: Development Status :: 4 - Beta
Classifier: Topic :: Text Processing :: Markup :: HTML
Classifier: Operating System :: OS Independent
Classifier: Typing :: Typed
Requires-Python: >=3.10
License-File: LICENSE
Requires-Dist: markupsafe>=2.0.0
Requires-Dist: typing_extensions>=4.13.2; python_version < "3.13"
Dynamic: license-file
